pyfuncbuffer/__init__.py
pyfuncbuffer/pyfuncbuffer.py
pyfuncbuffer-0.2.2.dist-info/LICENSE.txt
pyfuncbuffer-0.2.2.dist-info/METADATA
pyfuncbuffer-0.2.2.dist-info/WHEEL
pyfuncbuffer-0.2.2.dist-info/top_level.txt
pyfuncbuffer-0.2.2.dist-info/RECORD
