Metadata-Version: 2.1
Name: pyfuncbuffer
Version: 0.2.2
Summary: A library for buffering function calls
Home-page: https://github.com/Jupsista/pyfuncbuffer
Author: Jupsista
License: GPLv3
Platform: UNKNOWN
Classifier: Intended Audience :: Developers
Classifier: License :: OSI Approved :: GNU General Public License v3 (GPLv3)
Classifier: Operating System :: OS Independent
Classifier: Typing :: Typed
Classifier: Topic :: Software Development :: Libraries
Classifier: Programming Language :: Python :: 3
License-File: LICENSE.txt
